educode/__init__.py
educode/__main__.py
educode/auth.py
educode/certification.py
educode/core.py
educode/exercises.py
educode-1.1.1.dist-info/licenses/LICENSE
educode-1.1.1.dist-info/METADATA
educode-1.1.1.dist-info/WHEEL
educode-1.1.1.dist-info/entry_points.txt
educode-1.1.1.dist-info/top_level.txt
educode-1.1.1.dist-info/RECORD
