Metadata-Version: 2.4
Name: educode
Version: 1.1.1
Summary: Système interactif de +200 exercices pour apprendre Python
Home-page: https://github.com/Moesthetics-code/educode
Author: Mohamed Ndiaye
Author-email: mintok2000@gmail.com
Project-URL: Bug Reports, https://github.com/Moesthetics-code/educode/issues
Project-URL: Source, https://github.com/Moesthetics-code/educode
Project-URL: Documentation, https://educode.readthedocs.io/
Keywords: education,python,exercises,learning,programming,tutorial,practice
Classifier: Development Status :: 5 - Production/Stable
Classifier: Intended Audience :: Education
Classifier: Intended Audience :: Developers
Classifier: Topic :: Education
Classifier: Topic :: Software Development :: Libraries :: Python Modules
Classifier: License :: OSI Approved :: MIT License
Classifier: Programming Language :: Python :: 3
Classifier: Programming Language :: Python :: 3.6
Classifier: Programming Language :: Python :: 3.7
Classifier: Programming Language :: Python :: 3.8
Classifier: Programming Language :: Python :: 3.9
Classifier: Programming Language :: Python :: 3.10
Classifier: Programming Language :: Python :: 3.11
Requires-Python: >=3.6
License-File: LICENSE
Dynamic: author
Dynamic: author-email
Dynamic: classifier
Dynamic: description
Dynamic: description-content-type
Dynamic: home-page
Dynamic: keywords
Dynamic: license-file
Dynamic: project-url
Dynamic: requires-python
Dynamic: summary
